{
  "parent": "block/block",
  "textures": {
    "particle": "block/chain",
    "all": "block/chain"
  },
  "elements": [
    {
      "from": [ 6.5, 6.5, 8 ],
      "to": [ 9.5, 9.5, 8 ],
      "rotation": { "origin": [ 8, 8, 8 ], "axis": "y", "angle": 45},
      "shade": false,
      "faces": {
        "north": { "uv": [ 3, 6.5, 6, 9.5 ], "texture": "#all" },
        "south": { "uv": [ 3, 6.5, 6, 9.5 ], "texture": "#all" }
      }
    },
    {
      "from": [ 8, 6.5, 6.5 ],
      "to": [ 8, 9.5, 9.5 ],
      "rotation": { "origin": [ 8, 8, 8 ], "axis": "y", "angle": 45},
      "shade": false,
      "faces": {
        "west": { "uv": [ 0, 6.5, 3, 9.5 ], "texture": "#all" },
        "east": { "uv": [ 0, 6.5, 3, 9.5 ], "texture": "#all" }
      }
    }
  ]
}
